<?xml version="1.0" encoding="UTF-8" standalone="yes"?>
<!--
	
	Назначение файла: Описание и координаты расположения NPC
	========================================================

	Название локации: Брегирун
	Описание: 

	================================================================
	Разработка серверной части: Copyright (c) Aion-Knight, 2011-2012
	Веб-cайт разработчиков: http://aion-knight.ru
 
 -->
<spawns>
	<!-- 
	Название: Защитный камень пространственных врат
	Описание: Объект
	-->
	<spawn map="320030000" npcid="700142" pool="1" interval="295">
		<object staticid="75" x="261.35947" y="229.51807" z="213.92033" h="93" w="0" rw="0"/>
	</spawn>
	<!-- 
	Название: Пространственные врата
	Описание: Объект
	-->
	<spawn map="320030000" npcid="700141" pool="1" interval="295">
		<object x="250.8047" y="273.29163" z="230.087" h="92" w="0" rw="0"/>
	</spawn>
	<!-- 
	Название: Пространственные врата Альтгарда
	Описание: Объект
	-->
	<spawn map="320030000" npcid="700089" pool="1" interval="295">
		<object staticid="17" x="276.86542" y="159.01343" z="205.38808" h="34" w="0" rw="0"/>
	</spawn>
</spawns>